{"data":{"mdx":{"code":{"body":"function _extends() { _extends = Object.assign || function (target) { for (var i = 1; i < arguments.length; i++) { var source = arguments[i]; for (var key in source) { if (Object.prototype.hasOwnProperty.call(source, key)) { target[key] = source[key]; } } } return target; }; return _extends.apply(this, arguments); }\n\nfunction _objectWithoutProperties(source, excluded) { if (source == null) return {}; var target = _objectWithoutPropertiesLoose(source, excluded); var key, i; if (Object.getOwnPropertySymbols) { var sourceSymbolKeys = Object.getOwnPropertySymbols(source); for (i = 0; i < sourceSymbolKeys.length; i++) { key = sourceSymbolKeys[i]; if (excluded.indexOf(key) >= 0) continue; if (!Object.prototype.propertyIsEnumerable.call(source, key)) continue; target[key] = source[key]; } } return target; }\n\nfunction _objectWithoutPropertiesLoose(source, excluded) { if (source == null) return {}; var target = {}; var sourceKeys = Object.keys(source); var key, i; for (i = 0; i < sourceKeys.length; i++) { key = sourceKeys[i]; if (excluded.indexOf(key) >= 0) continue; target[key] = source[key]; } return target; }\n\n/* @jsx mdx */\nvar _frontmatter = {\n  \"title\": \"Pagination\",\n  \"tabs\": [\"Code\", \"Usage\", \"Style\"]\n};\n\nvar makeShortcode = function makeShortcode(name) {\n  return function MDXDefaultShortcode(props) {\n    console.warn(\"Component \" + name + \" was not imported, exported, or provided by MDXProvider as global scope\");\n    return mdx(\"div\", props);\n  };\n};\n\nvar ImageComponent = makeShortcode(\"ImageComponent\");\nvar layoutProps = {\n  _frontmatter: _frontmatter\n};\nvar MDXLayout = \"wrapper\";\nreturn function MDXContent(_ref) {\n  var components = _ref.components,\n      props = _objectWithoutProperties(_ref, [\"components\"]);\n\n  return mdx(MDXLayout, _extends({}, layoutProps, props, {\n    components: components,\n    mdxType: \"MDXLayout\"\n  }), mdx(\"h2\", null, \"Color\"), mdx(\"table\", null, mdx(\"thead\", {\n    parentName: \"table\"\n  }, mdx(\"tr\", {\n    parentName: \"thead\"\n  }, mdx(\"th\", _extends({\n    parentName: \"tr\"\n  }, {\n    \"align\": null\n  }), \"Class\"), mdx(\"th\", _extends({\n    parentName: \"tr\"\n  }, {\n    \"align\": null\n  }), \"Property\"), mdx(\"th\", _extends({\n    parentName: \"tr\"\n  }, {\n    \"align\": null\n  }), \"Color token\"))), mdx(\"tbody\", {\n    parentName: \"table\"\n  }, mdx(\"tr\", {\n    parentName: \"tbody\"\n  }, mdx(\"td\", _extends({\n    parentName: \"tr\"\n  }, {\n    \"align\": null\n  }), mdx(\"inlineCode\", {\n    parentName: \"td\"\n  }, \".bx--pagination\")), mdx(\"td\", _extends({\n    parentName: \"tr\"\n  }, {\n    \"align\": null\n  }), \"background-color\"), mdx(\"td\", _extends({\n    parentName: \"tr\"\n  }, {\n    \"align\": null\n  }), mdx(\"inlineCode\", {\n    parentName: \"td\"\n  }, \"$ui-01\"))), mdx(\"tr\", {\n    parentName: \"tbody\"\n  }, mdx(\"td\", _extends({\n    parentName: \"tr\"\n  }, {\n    \"align\": null\n  }), mdx(\"inlineCode\", {\n    parentName: \"td\"\n  }, \".bx--pagination\")), mdx(\"td\", _extends({\n    parentName: \"tr\"\n  }, {\n    \"align\": null\n  }), \"border-top\"), mdx(\"td\", _extends({\n    parentName: \"tr\"\n  }, {\n    \"align\": null\n  }), mdx(\"inlineCode\", {\n    parentName: \"td\"\n  }, \"$ui-03\"))), mdx(\"tr\", {\n    parentName: \"tbody\"\n  }, mdx(\"td\", _extends({\n    parentName: \"tr\"\n  }, {\n    \"align\": null\n  }), mdx(\"inlineCode\", {\n    parentName: \"td\"\n  }, \".bx--pagination__text\")), mdx(\"td\", _extends({\n    parentName: \"tr\"\n  }, {\n    \"align\": null\n  }), \"text color\"), mdx(\"td\", _extends({\n    parentName: \"tr\"\n  }, {\n    \"align\": null\n  }), mdx(\"inlineCode\", {\n    parentName: \"td\"\n  }, \"$text-02\"))), mdx(\"tr\", {\n    parentName: \"tbody\"\n  }, mdx(\"td\", _extends({\n    parentName: \"tr\"\n  }, {\n    \"align\": null\n  }), mdx(\"inlineCode\", {\n    parentName: \"td\"\n  }, \".bx--pagination__button-icon\")), mdx(\"td\", _extends({\n    parentName: \"tr\"\n  }, {\n    \"align\": null\n  }), \"fill\"), mdx(\"td\", _extends({\n    parentName: \"tr\"\n  }, {\n    \"align\": null\n  }), mdx(\"inlineCode\", {\n    parentName: \"td\"\n  }, \"$icon-01\"))))), mdx(\"h2\", null, \"Typography\"), mdx(\"p\", null, \"Pagination text should be set in set in sentence case with the first letter of each word capitalized.\"), mdx(\"table\", null, mdx(\"thead\", {\n    parentName: \"table\"\n  }, mdx(\"tr\", {\n    parentName: \"thead\"\n  }, mdx(\"th\", _extends({\n    parentName: \"tr\"\n  }, {\n    \"align\": null\n  }), \"Class\"), mdx(\"th\", _extends({\n    parentName: \"tr\"\n  }, {\n    \"align\": null\n  }), \"Font-size (px/rem)\"), mdx(\"th\", _extends({\n    parentName: \"tr\"\n  }, {\n    \"align\": null\n  }), \"Font-weight\"), mdx(\"th\", _extends({\n    parentName: \"tr\"\n  }, {\n    \"align\": null\n  }), \"Type token\"))), mdx(\"tbody\", {\n    parentName: \"table\"\n  }, mdx(\"tr\", {\n    parentName: \"tbody\"\n  }, mdx(\"td\", _extends({\n    parentName: \"tr\"\n  }, {\n    \"align\": null\n  }), mdx(\"inlineCode\", {\n    parentName: \"td\"\n  }, \".bx--pagination__text\")), mdx(\"td\", _extends({\n    parentName: \"tr\"\n  }, {\n    \"align\": null\n  }), \"12 / 0.75\"), mdx(\"td\", _extends({\n    parentName: \"tr\"\n  }, {\n    \"align\": null\n  }), \"Regular / 400\"), mdx(\"td\", _extends({\n    parentName: \"tr\"\n  }, {\n    \"align\": null\n  }), mdx(\"inlineCode\", {\n    parentName: \"td\"\n  }, \"$caption-01\"))))), mdx(\"h2\", null, \"Structure\"), mdx(\"p\", null, \"The Pagination bar is most commonly used in data tables. The width can vary depending on content and layout, but should span the entire width of the table it\\u2019s being paired with. \"), mdx(\"table\", null, mdx(\"thead\", {\n    parentName: \"table\"\n  }, mdx(\"tr\", {\n    parentName: \"thead\"\n  }, mdx(\"th\", _extends({\n    parentName: \"tr\"\n  }, {\n    \"align\": null\n  }), \"Class\"), mdx(\"th\", _extends({\n    parentName: \"tr\"\n  }, {\n    \"align\": null\n  }), \"Property\"), mdx(\"th\", _extends({\n    parentName: \"tr\"\n  }, {\n    \"align\": null\n  }), \"px / rem\"), mdx(\"th\", _extends({\n    parentName: \"tr\"\n  }, {\n    \"align\": null\n  }), \"Spacing token\"))), mdx(\"tbody\", {\n    parentName: \"table\"\n  }, mdx(\"tr\", {\n    parentName: \"tbody\"\n  }, mdx(\"td\", _extends({\n    parentName: \"tr\"\n  }, {\n    \"align\": null\n  }), mdx(\"inlineCode\", {\n    parentName: \"td\"\n  }, \".bx--pagination\")), mdx(\"td\", _extends({\n    parentName: \"tr\"\n  }, {\n    \"align\": null\n  }), \"height\"), mdx(\"td\", _extends({\n    parentName: \"tr\"\n  }, {\n    \"align\": null\n  }), \"48 / 3\"), mdx(\"td\", _extends({\n    parentName: \"tr\"\n  }, {\n    \"align\": null\n  }), \"\\u2013\")), mdx(\"tr\", {\n    parentName: \"tbody\"\n  }, mdx(\"td\", _extends({\n    parentName: \"tr\"\n  }, {\n    \"align\": null\n  }), mdx(\"inlineCode\", {\n    parentName: \"td\"\n  }, \".bx--pagination\")), mdx(\"td\", _extends({\n    parentName: \"tr\"\n  }, {\n    \"align\": null\n  }), \"border\"), mdx(\"td\", _extends({\n    parentName: \"tr\"\n  }, {\n    \"align\": null\n  }), \"1px\"), mdx(\"td\", _extends({\n    parentName: \"tr\"\n  }, {\n    \"align\": null\n  }), \"\\u2013\")), mdx(\"tr\", {\n    parentName: \"tbody\"\n  }, mdx(\"td\", _extends({\n    parentName: \"tr\"\n  }, {\n    \"align\": null\n  }), mdx(\"inlineCode\", {\n    parentName: \"td\"\n  }, \".bx--pagination\")), mdx(\"td\", _extends({\n    parentName: \"tr\"\n  }, {\n    \"align\": null\n  }), \"padding-left, padding-right\"), mdx(\"td\", _extends({\n    parentName: \"tr\"\n  }, {\n    \"align\": null\n  }), \"16 / 1\"), mdx(\"td\", _extends({\n    parentName: \"tr\"\n  }, {\n    \"align\": null\n  }), mdx(\"inlineCode\", {\n    parentName: \"td\"\n  }, \"$spacing-05\"))), mdx(\"tr\", {\n    parentName: \"tbody\"\n  }, mdx(\"td\", _extends({\n    parentName: \"tr\"\n  }, {\n    \"align\": null\n  }), mdx(\"inlineCode\", {\n    parentName: \"td\"\n  }, \".bx--pagination .bx--select-input\")), mdx(\"td\", _extends({\n    parentName: \"tr\"\n  }, {\n    \"align\": null\n  }), \"padding-left, padding-right\"), mdx(\"td\", _extends({\n    parentName: \"tr\"\n  }, {\n    \"align\": null\n  }), \"16 / 1\"), mdx(\"td\", _extends({\n    parentName: \"tr\"\n  }, {\n    \"align\": null\n  }), mdx(\"inlineCode\", {\n    parentName: \"td\"\n  }, \"$spacing-05\"))), mdx(\"tr\", {\n    parentName: \"tbody\"\n  }, mdx(\"td\", _extends({\n    parentName: \"tr\"\n  }, {\n    \"align\": null\n  }), mdx(\"inlineCode\", {\n    parentName: \"td\"\n  }, \".bx--pagination__button\")), mdx(\"td\", _extends({\n    parentName: \"tr\"\n  }, {\n    \"align\": null\n  }), \"height, width\"), mdx(\"td\", _extends({\n    parentName: \"tr\"\n  }, {\n    \"align\": null\n  }), \"16 / 1\"), mdx(\"td\", _extends({\n    parentName: \"tr\"\n  }, {\n    \"align\": null\n  }), \"\\u2013\")), mdx(\"tr\", {\n    parentName: \"tbody\"\n  }, mdx(\"td\", _extends({\n    parentName: \"tr\"\n  }, {\n    \"align\": null\n  }), mdx(\"inlineCode\", {\n    parentName: \"td\"\n  }, \"arrow\")), mdx(\"td\", _extends({\n    parentName: \"tr\"\n  }, {\n    \"align\": null\n  }), \"icon size\"), mdx(\"td\", _extends({\n    parentName: \"tr\"\n  }, {\n    \"align\": null\n  }), \"20 x 20px\"), mdx(\"td\", _extends({\n    parentName: \"tr\"\n  }, {\n    \"align\": null\n  }), \"\\u2013\")))), mdx(ImageComponent, {\n    fixed: \"large\",\n    caption: \"Structure and spacing measurements for Pagination | px / rem\",\n    mdxType: \"ImageComponent\"\n  }, mdx(\"span\", {\n    \"className\": \"gatsby-resp-image-wrapper\",\n    \"style\": {\n      \"position\": \"relative\",\n      \"display\": \"block\",\n      \"maxWidth\": \"1120px\",\n      \"marginLeft\": \"auto\",\n      \"marginRight\": \"auto\"\n    }\n  }, \"\\n    \", mdx(\"span\", _extends({\n    parentName: \"span\"\n  }, {\n    \"className\": \"gatsby-resp-image-background-image\",\n    \"style\": {\n      \"paddingBottom\": \"31.696428571428577%\",\n      \"position\": \"relative\",\n      \"bottom\": \"0px\",\n      \"left\": \"0px\",\n      \"backgroundSize\": \"cover\",\n      \"display\": \"block\"\n    }\n  })), \"\\n    \", mdx(\"img\", _extends({\n    parentName: \"span\"\n  }, {\n    \"className\": \"gatsby-resp-image-image\",\n    \"style\": {\n      \"width\": \"100%\",\n      \"height\": \"100%\",\n      \"margin\": \"0px\",\n      \"verticalAlign\": \"middle\",\n      \"position\": \"absolute\",\n      \"top\": \"0px\",\n      \"left\": \"0px\",\n      \"boxShadow\": \"inset 0px 0px 0px 400px transparent\"\n    },\n    \"alt\": \"Structure and spacing for pagination\",\n    \"title\": \"\",\n    \"src\": \"/static/b21b09981fe63228b576b74c8ff9126c/24bd0/pagination-style-1.png\",\n    \"srcSet\": [\"/static/b21b09981fe63228b576b74c8ff9126c/7cb4c/pagination-style-1.png 280w\", \"/static/b21b09981fe63228b576b74c8ff9126c/7ff44/pagination-style-1.png 560w\", \"/static/b21b09981fe63228b576b74c8ff9126c/24bd0/pagination-style-1.png 1120w\", \"/static/b21b09981fe63228b576b74c8ff9126c/7e58d/pagination-style-1.png 1680w\", \"/static/b21b09981fe63228b576b74c8ff9126c/8ef2b/pagination-style-1.png 2240w\"],\n    \"sizes\": \"(max-width: 1120px) 100vw, 1120px\"\n  })), \"\\n  \")));\n}\nMDXContent.isMDXComponent = true;"},"fields":{"slug":"/components/pagination/style","currentPage":"style"},"frontmatter":{"title":"Pagination","label":null,"tabs":["Code","Usage","Style"],"internal":null}}},"pageContext":{"slug":"/components/pagination/style","currentPage":"style"}}