{"data":{"mdx":{"code":{"body":"function _extends() { _extends = Object.assign || function (target) { for (var i = 1; i < arguments.length; i++) { var source = arguments[i]; for (var key in source) { if (Object.prototype.hasOwnProperty.call(source, key)) { target[key] = source[key]; } } } return target; }; return _extends.apply(this, arguments); }\n\nfunction _objectWithoutProperties(source, excluded) { if (source == null) return {}; var target = _objectWithoutPropertiesLoose(source, excluded); var key, i; if (Object.getOwnPropertySymbols) { var sourceSymbolKeys = Object.getOwnPropertySymbols(source); for (i = 0; i < sourceSymbolKeys.length; i++) { key = sourceSymbolKeys[i]; if (excluded.indexOf(key) >= 0) continue; if (!Object.prototype.propertyIsEnumerable.call(source, key)) continue; target[key] = source[key]; } } return target; }\n\nfunction _objectWithoutPropertiesLoose(source, excluded) { if (source == null) return {}; var target = {}; var sourceKeys = Object.keys(source); var key, i; for (i = 0; i < sourceKeys.length; i++) { key = sourceKeys[i]; if (excluded.indexOf(key) >= 0) continue; target[key] = source[key]; } return target; }\n\n/* @jsx mdx */\nvar _frontmatter = {\n  \"title\": \"Data table\",\n  \"tabs\": [\"Code\", \"Usage\", \"Style\"]\n};\n\nvar makeShortcode = function makeShortcode(name) {\n  return function MDXDefaultShortcode(props) {\n    console.warn(\"Component \" + name + \" was not imported, exported, or provided by MDXProvider as global scope\");\n    return mdx(\"div\", props);\n  };\n};\n\nvar ImageComponent = makeShortcode(\"ImageComponent\");\nvar layoutProps = {\n  _frontmatter: _frontmatter\n};\nvar MDXLayout = \"wrapper\";\nreturn function MDXContent(_ref) {\n  var components = _ref.components,\n      props = _objectWithoutProperties(_ref, [\"components\"]);\n\n  return mdx(MDXLayout, _extends({}, layoutProps, props, {\n    components: components,\n    mdxType: \"MDXLayout\"\n  }), mdx(\"h2\", null, \"Basic data table\"), mdx(\"p\", null, \"The data table component is designed in a way for additional functionality to be added on to fit your team\\u2019s needs.\"), mdx(\"p\", null, \"The basic data table is shipped with a base style, which includes:\"), mdx(\"ul\", null, mdx(\"li\", {\n    parentName: \"ul\"\n  }, \"Borders\"), mdx(\"li\", {\n    parentName: \"ul\"\n  }, \"No zebra striping, row dividers instead.\"), mdx(\"li\", {\n    parentName: \"ul\"\n  }, \"No Pagination, search, table toolbar, or multi-select\")), mdx(ImageComponent, {\n    fixed: \"default\",\n    caption: \"Basic data table\",\n    mdxType: \"ImageComponent\"\n  }, mdx(\"span\", {\n    \"className\": \"gatsby-resp-image-wrapper\",\n    \"style\": {\n      \"position\": \"relative\",\n      \"display\": \"block\",\n      \"maxWidth\": \"1120px\",\n      \"marginLeft\": \"auto\",\n      \"marginRight\": \"auto\"\n    }\n  }, \"\\n    \", mdx(\"span\", _extends({\n    parentName: \"span\"\n  }, {\n    \"className\": \"gatsby-resp-image-background-image\",\n    \"style\": {\n      \"paddingBottom\": \"72.82608695652173%\",\n      \"position\": \"relative\",\n      \"bottom\": \"0px\",\n      \"left\": \"0px\",\n      \"backgroundSize\": \"cover\",\n      \"display\": \"block\"\n    }\n  })), \"\\n    \", mdx(\"img\", _extends({\n    parentName: \"span\"\n  }, {\n    \"className\": \"gatsby-resp-image-image\",\n    \"style\": {\n      \"width\": \"100%\",\n      \"height\": \"100%\",\n      \"margin\": \"0px\",\n      \"verticalAlign\": \"middle\",\n      \"position\": \"absolute\",\n      \"top\": \"0px\",\n      \"left\": \"0px\",\n      \"boxShadow\": \"inset 0px 0px 0px 400px transparent\"\n    },\n    \"alt\": \"basic data table\",\n    \"title\": \"\",\n    \"src\": \"/static/786fc67ab286a09696016dbdb2133ad9/24bd0/data-table-usage-1.png\",\n    \"srcSet\": [\"/static/786fc67ab286a09696016dbdb2133ad9/7cb4c/data-table-usage-1.png 280w\", \"/static/786fc67ab286a09696016dbdb2133ad9/7ff44/data-table-usage-1.png 560w\", \"/static/786fc67ab286a09696016dbdb2133ad9/24bd0/data-table-usage-1.png 1120w\", \"/static/786fc67ab286a09696016dbdb2133ad9/b4af2/data-table-usage-1.png 1472w\"],\n    \"sizes\": \"(max-width: 1120px) 100vw, 1120px\"\n  })), \"\\n  \")), mdx(\"h2\", null, \"Additional functionality\"), mdx(\"p\", null, \"The following can be added to the data table to increase its functionality.\"), mdx(\"h3\", null, \"Pagination\"), mdx(\"p\", null, \"Pagination divides table data into separate pages. Pagination is accompanied by an option that enables the user to change the number of items per page. See the \", mdx(\"a\", _extends({\n    parentName: \"p\"\n  }, {\n    \"href\": \"/components/Pagination\"\n  }), \"pagination\"), \" component for further guidelines.\"), mdx(ImageComponent, {\n    fixed: \"default\",\n    caption: \"Data table with various Pagination methods\",\n    mdxType: \"ImageComponent\"\n  }, mdx(\"span\", {\n    \"className\": \"gatsby-resp-image-wrapper\",\n    \"style\": {\n      \"position\": \"relative\",\n      \"display\": \"block\",\n      \"maxWidth\": \"1120px\",\n      \"marginLeft\": \"auto\",\n      \"marginRight\": \"auto\"\n    }\n  }, \"\\n    \", mdx(\"span\", _extends({\n    parentName: \"span\"\n  }, {\n    \"className\": \"gatsby-resp-image-background-image\",\n    \"style\": {\n      \"paddingBottom\": \"105.43478260869566%\",\n      \"position\": \"relative\",\n      \"bottom\": \"0px\",\n      \"left\": \"0px\",\n      \"backgroundSize\": \"cover\",\n      \"display\": \"block\"\n    }\n  })), \"\\n    \", mdx(\"img\", _extends({\n    parentName: \"span\"\n  }, {\n    \"className\": \"gatsby-resp-image-image\",\n    \"style\": {\n      \"width\": \"100%\",\n      \"height\": \"100%\",\n      \"margin\": \"0px\",\n      \"verticalAlign\": \"middle\",\n      \"position\": \"absolute\",\n      \"top\": \"0px\",\n      \"left\": \"0px\",\n      \"boxShadow\": \"inset 0px 0px 0px 400px transparent\"\n    },\n    \"alt\": \"data table with pagination\",\n    \"title\": \"\",\n    \"src\": \"/static/d0132152e185afb3320e0999581f5799/24bd0/data-table-usage-2.png\",\n    \"srcSet\": [\"/static/d0132152e185afb3320e0999581f5799/7cb4c/data-table-usage-2.png 280w\", \"/static/d0132152e185afb3320e0999581f5799/7ff44/data-table-usage-2.png 560w\", \"/static/d0132152e185afb3320e0999581f5799/24bd0/data-table-usage-2.png 1120w\", \"/static/d0132152e185afb3320e0999581f5799/b4af2/data-table-usage-2.png 1472w\"],\n    \"sizes\": \"(max-width: 1120px) 100vw, 1120px\"\n  })), \"\\n  \")), mdx(\"h3\", null, \"Search\"), mdx(\"p\", null, \"Search returns results based on matches. It is used to locate and display a set of results. Search functionality within a table follows \", mdx(\"a\", _extends({\n    parentName: \"p\"\n  }, {\n    \"href\": \"/components/search\"\n  }), \"small search\"), \" conventions. Search should be closed by default, and live below the table title.\"), mdx(ImageComponent, {\n    fixed: \"default\",\n    caption: \"Search on data tables.\",\n    mdxType: \"ImageComponent\"\n  }, mdx(\"span\", {\n    \"className\": \"gatsby-resp-image-wrapper\",\n    \"style\": {\n      \"position\": \"relative\",\n      \"display\": \"block\",\n      \"maxWidth\": \"1120px\",\n      \"marginLeft\": \"auto\",\n      \"marginRight\": \"auto\"\n    }\n  }, \"\\n    \", mdx(\"span\", _extends({\n    parentName: \"span\"\n  }, {\n    \"className\": \"gatsby-resp-image-background-image\",\n    \"style\": {\n      \"paddingBottom\": \"155.70652173913044%\",\n      \"position\": \"relative\",\n      \"bottom\": \"0px\",\n      \"left\": \"0px\",\n      \"backgroundSize\": \"cover\",\n      \"display\": \"block\"\n    }\n  })), \"\\n    \", mdx(\"img\", _extends({\n    parentName: \"span\"\n  }, {\n    \"className\": \"gatsby-resp-image-image\",\n    \"style\": {\n      \"width\": \"100%\",\n      \"height\": \"100%\",\n      \"margin\": \"0px\",\n      \"verticalAlign\": \"middle\",\n      \"position\": \"absolute\",\n      \"top\": \"0px\",\n      \"left\": \"0px\",\n      \"boxShadow\": \"inset 0px 0px 0px 400px transparent\"\n    },\n    \"alt\": \"data table with search\",\n    \"title\": \"\",\n    \"src\": \"/static/aac2fd77a84147a8ae1a58ddd90d7884/24bd0/data-table-usage-3.png\",\n    \"srcSet\": [\"/static/aac2fd77a84147a8ae1a58ddd90d7884/7cb4c/data-table-usage-3.png 280w\", \"/static/aac2fd77a84147a8ae1a58ddd90d7884/7ff44/data-table-usage-3.png 560w\", \"/static/aac2fd77a84147a8ae1a58ddd90d7884/24bd0/data-table-usage-3.png 1120w\", \"/static/aac2fd77a84147a8ae1a58ddd90d7884/b4af2/data-table-usage-3.png 1472w\"],\n    \"sizes\": \"(max-width: 1120px) 100vw, 1120px\"\n  })), \"\\n  \")), mdx(\"h3\", null, \"Sorting\"), mdx(\"p\", null, \"Improve table usability by making data sortable. Clickable headers enable users to sort table data up or down. The specific attribute being sorted is accompanied by a caret icon. The caret will only appear on the column headers once that particular column is being sorted. You can see a demo of this on Carbon\\u2019s \", mdx(\"a\", _extends({\n    parentName: \"p\"\n  }, {\n    \"href\": \"https://codepen.io/tjegan/pen/PjjyVN\"\n  }), \"Codepen.\")), mdx(\"h3\", null, \"Table toolbar\"), mdx(\"p\", null, \"The table toolbar is reserved for global table actions such as table settings, complex filter, export, or editing table data. Additional options can be added if you have an icon to support that function. Icons should be 16x16 px (glyphs). We recommend using no more than 5 icons within the table toolbar.\"), mdx(ImageComponent, {\n    fixed: \"default\",\n    caption: \"Table toolbar: table settings\",\n    mdxType: \"ImageComponent\"\n  }, mdx(\"span\", {\n    \"className\": \"gatsby-resp-image-wrapper\",\n    \"style\": {\n      \"position\": \"relative\",\n      \"display\": \"block\",\n      \"maxWidth\": \"1120px\",\n      \"marginLeft\": \"auto\",\n      \"marginRight\": \"auto\"\n    }\n  }, \"\\n    \", mdx(\"span\", _extends({\n    parentName: \"span\"\n  }, {\n    \"className\": \"gatsby-resp-image-background-image\",\n    \"style\": {\n      \"paddingBottom\": \"59.91847826086957%\",\n      \"position\": \"relative\",\n      \"bottom\": \"0px\",\n      \"left\": \"0px\",\n      \"backgroundSize\": \"cover\",\n      \"display\": \"block\"\n    }\n  })), \"\\n    \", mdx(\"img\", _extends({\n    parentName: \"span\"\n  }, {\n    \"className\": \"gatsby-resp-image-image\",\n    \"style\": {\n      \"width\": \"100%\",\n      \"height\": \"100%\",\n      \"margin\": \"0px\",\n      \"verticalAlign\": \"middle\",\n      \"position\": \"absolute\",\n      \"top\": \"0px\",\n      \"left\": \"0px\",\n      \"boxShadow\": \"inset 0px 0px 0px 400px transparent\"\n    },\n    \"alt\": \"Table toolbar\",\n    \"title\": \"\",\n    \"src\": \"/static/0675b4f676975d0cf9e88e19eab010d9/24bd0/data-table-usage-6.png\",\n    \"srcSet\": [\"/static/0675b4f676975d0cf9e88e19eab010d9/7cb4c/data-table-usage-6.png 280w\", \"/static/0675b4f676975d0cf9e88e19eab010d9/7ff44/data-table-usage-6.png 560w\", \"/static/0675b4f676975d0cf9e88e19eab010d9/24bd0/data-table-usage-6.png 1120w\", \"/static/0675b4f676975d0cf9e88e19eab010d9/b4af2/data-table-usage-6.png 1472w\"],\n    \"sizes\": \"(max-width: 1120px) 100vw, 1120px\"\n  })), \"\\n  \")), mdx(\"h3\", null, \"Multi-select / batch action\"), mdx(\"p\", null, \"Batch actions are functions that may be performed on multiple items within a table. Once the user selects at least one row from the table, the \", mdx(\"strong\", {\n    parentName: \"p\"\n  }, \"batch action bar\"), \" appears at the top of the table, presenting the user with actions they can take. To exit or escape \\u201Cbatch action mode,\\u201D the user can cancel out or deselect the items.\"), mdx(ImageComponent, {\n    fixed: \"default\",\n    caption: \"Batch action mode on data tables\",\n    mdxType: \"ImageComponent\"\n  }, mdx(\"span\", {\n    \"className\": \"gatsby-resp-image-wrapper\",\n    \"style\": {\n      \"position\": \"relative\",\n      \"display\": \"block\",\n      \"maxWidth\": \"1120px\",\n      \"marginLeft\": \"auto\",\n      \"marginRight\": \"auto\"\n    }\n  }, \"\\n    \", mdx(\"span\", _extends({\n    parentName: \"span\"\n  }, {\n    \"className\": \"gatsby-resp-image-background-image\",\n    \"style\": {\n      \"paddingBottom\": \"85.86956521739131%\",\n      \"position\": \"relative\",\n      \"bottom\": \"0px\",\n      \"left\": \"0px\",\n      \"backgroundSize\": \"cover\",\n      \"display\": \"block\"\n    }\n  })), \"\\n    \", mdx(\"img\", _extends({\n    parentName: \"span\"\n  }, {\n    \"className\": \"gatsby-resp-image-image\",\n    \"style\": {\n      \"width\": \"100%\",\n      \"height\": \"100%\",\n      \"margin\": \"0px\",\n      \"verticalAlign\": \"middle\",\n      \"position\": \"absolute\",\n      \"top\": \"0px\",\n      \"left\": \"0px\",\n      \"boxShadow\": \"inset 0px 0px 0px 400px transparent\"\n    },\n    \"alt\": \"Batch action mode\",\n    \"title\": \"\",\n    \"src\": \"/static/0fc0f85d31d627807b3bbfd228ffeb92/24bd0/data-table-usage-7.png\",\n    \"srcSet\": [\"/static/0fc0f85d31d627807b3bbfd228ffeb92/7cb4c/data-table-usage-7.png 280w\", \"/static/0fc0f85d31d627807b3bbfd228ffeb92/7ff44/data-table-usage-7.png 560w\", \"/static/0fc0f85d31d627807b3bbfd228ffeb92/24bd0/data-table-usage-7.png 1120w\", \"/static/0fc0f85d31d627807b3bbfd228ffeb92/b4af2/data-table-usage-7.png 1472w\"],\n    \"sizes\": \"(max-width: 1120px) 100vw, 1120px\"\n  })), \"\\n  \")), mdx(\"h3\", null, \"Inline actions\"), mdx(\"p\", null, \"Inline actions are functions that may be performed on a specific table item. Each row is accompanied by an \", mdx(\"a\", _extends({\n    parentName: \"p\"\n  }, {\n    \"href\": \"/components/overflow-menu\"\n  }), \"overflow menu\"), \" that contains actions related specifically to that table row.\"), mdx(ImageComponent, {\n    fixed: \"default\",\n    caption: \"Overflow menu example\",\n    mdxType: \"ImageComponent\"\n  }, mdx(\"span\", {\n    \"className\": \"gatsby-resp-image-wrapper\",\n    \"style\": {\n      \"position\": \"relative\",\n      \"display\": \"block\",\n      \"maxWidth\": \"1120px\",\n      \"marginLeft\": \"auto\",\n      \"marginRight\": \"auto\"\n    }\n  }, \"\\n    \", mdx(\"span\", _extends({\n    parentName: \"span\"\n  }, {\n    \"className\": \"gatsby-resp-image-background-image\",\n    \"style\": {\n      \"paddingBottom\": \"79.34782608695653%\",\n      \"position\": \"relative\",\n      \"bottom\": \"0px\",\n      \"left\": \"0px\",\n      \"backgroundSize\": \"cover\",\n      \"display\": \"block\"\n    }\n  })), \"\\n    \", mdx(\"img\", _extends({\n    parentName: \"span\"\n  }, {\n    \"className\": \"gatsby-resp-image-image\",\n    \"style\": {\n      \"width\": \"100%\",\n      \"height\": \"100%\",\n      \"margin\": \"0px\",\n      \"verticalAlign\": \"middle\",\n      \"position\": \"absolute\",\n      \"top\": \"0px\",\n      \"left\": \"0px\",\n      \"boxShadow\": \"inset 0px 0px 0px 400px transparent\"\n    },\n    \"alt\": \"Overflow menu example\",\n    \"title\": \"\",\n    \"src\": \"/static/9bb5bb02c111a0431efd21e04d84fd27/24bd0/data-table-usage-8.png\",\n    \"srcSet\": [\"/static/9bb5bb02c111a0431efd21e04d84fd27/7cb4c/data-table-usage-8.png 280w\", \"/static/9bb5bb02c111a0431efd21e04d84fd27/7ff44/data-table-usage-8.png 560w\", \"/static/9bb5bb02c111a0431efd21e04d84fd27/24bd0/data-table-usage-8.png 1120w\", \"/static/9bb5bb02c111a0431efd21e04d84fd27/b4af2/data-table-usage-8.png 1472w\"],\n    \"sizes\": \"(max-width: 1120px) 100vw, 1120px\"\n  })), \"\\n  \")), mdx(\"p\", null, \"When the overflow menu contains less than three options, keep the actions inline as icon buttons instead. This reduces 1 click and makes available actions visible to users at a glance.\"), mdx(ImageComponent, {\n    fixed: \"default\",\n    caption: \"Inline actions without overflow\",\n    mdxType: \"ImageComponent\"\n  }, mdx(\"span\", {\n    \"className\": \"gatsby-resp-image-wrapper\",\n    \"style\": {\n      \"position\": \"relative\",\n      \"display\": \"block\",\n      \"maxWidth\": \"1120px\",\n      \"marginLeft\": \"auto\",\n      \"marginRight\": \"auto\"\n    }\n  }, \"\\n    \", mdx(\"span\", _extends({\n    parentName: \"span\"\n  }, {\n    \"className\": \"gatsby-resp-image-background-image\",\n    \"style\": {\n      \"paddingBottom\": \"79.34782608695653%\",\n      \"position\": \"relative\",\n      \"bottom\": \"0px\",\n      \"left\": \"0px\",\n      \"backgroundSize\": \"cover\",\n      \"display\": \"block\"\n    }\n  })), \"\\n    \", mdx(\"img\", _extends({\n    parentName: \"span\"\n  }, {\n    \"className\": \"gatsby-resp-image-image\",\n    \"style\": {\n      \"width\": \"100%\",\n      \"height\": \"100%\",\n      \"margin\": \"0px\",\n      \"verticalAlign\": \"middle\",\n      \"position\": \"absolute\",\n      \"top\": \"0px\",\n      \"left\": \"0px\",\n      \"boxShadow\": \"inset 0px 0px 0px 400px transparent\"\n    },\n    \"alt\": \"Inline actions without overflow\",\n    \"title\": \"\",\n    \"src\": \"/static/9ee36ddb1e5d2e9286b85ec92a1dfe3a/24bd0/data-table-usage-10.png\",\n    \"srcSet\": [\"/static/9ee36ddb1e5d2e9286b85ec92a1dfe3a/7cb4c/data-table-usage-10.png 280w\", \"/static/9ee36ddb1e5d2e9286b85ec92a1dfe3a/7ff44/data-table-usage-10.png 560w\", \"/static/9ee36ddb1e5d2e9286b85ec92a1dfe3a/24bd0/data-table-usage-10.png 1120w\", \"/static/9ee36ddb1e5d2e9286b85ec92a1dfe3a/b4af2/data-table-usage-10.png 1472w\"],\n    \"sizes\": \"(max-width: 1120px) 100vw, 1120px\"\n  })), \"\\n  \")), mdx(\"h4\", null, \"Persistent overflow menu\"), mdx(\"p\", null, \"By default, the overflow menu icon appears on hover or focus. This reduces visual clutter and drives user interactions with clear context and results.\"), mdx(\"p\", null, \"Data table also supports persistent overflow menu icons. Overflow icons should only persist if the actions contained within them are core to the function of your table. Enabling persistent overflow icons may complicate data presentation and impact general usability.\"), mdx(ImageComponent, {\n    fixed: \"default\",\n    caption: \"Persistent overflow menu icon example\",\n    mdxType: \"ImageComponent\"\n  }, mdx(\"span\", {\n    \"className\": \"gatsby-resp-image-wrapper\",\n    \"style\": {\n      \"position\": \"relative\",\n      \"display\": \"block\",\n      \"maxWidth\": \"1120px\",\n      \"marginLeft\": \"auto\",\n      \"marginRight\": \"auto\"\n    }\n  }, \"\\n    \", mdx(\"span\", _extends({\n    parentName: \"span\"\n  }, {\n    \"className\": \"gatsby-resp-image-background-image\",\n    \"style\": {\n      \"paddingBottom\": \"79.34782608695653%\",\n      \"position\": \"relative\",\n      \"bottom\": \"0px\",\n      \"left\": \"0px\",\n      \"backgroundSize\": \"cover\",\n      \"display\": \"block\"\n    }\n  })), \"\\n    \", mdx(\"img\", _extends({\n    parentName: \"span\"\n  }, {\n    \"className\": \"gatsby-resp-image-image\",\n    \"style\": {\n      \"width\": \"100%\",\n      \"height\": \"100%\",\n      \"margin\": \"0px\",\n      \"verticalAlign\": \"middle\",\n      \"position\": \"absolute\",\n      \"top\": \"0px\",\n      \"left\": \"0px\",\n      \"boxShadow\": \"inset 0px 0px 0px 400px transparent\"\n    },\n    \"alt\": \"Persistent overflow icon example\",\n    \"title\": \"\",\n    \"src\": \"/static/e3123ed00716d657e99eef5a29891f76/24bd0/data-table-usage-9.png\",\n    \"srcSet\": [\"/static/e3123ed00716d657e99eef5a29891f76/7cb4c/data-table-usage-9.png 280w\", \"/static/e3123ed00716d657e99eef5a29891f76/7ff44/data-table-usage-9.png 560w\", \"/static/e3123ed00716d657e99eef5a29891f76/24bd0/data-table-usage-9.png 1120w\", \"/static/e3123ed00716d657e99eef5a29891f76/b4af2/data-table-usage-9.png 1472w\"],\n    \"sizes\": \"(max-width: 1120px) 100vw, 1120px\"\n  })), \"\\n  \")), mdx(\"h3\", null, \"Expandable\"), mdx(\"p\", null, \"The expandable data table is useful for presenting large amounts of data in a small space. Use the expanded section for suplementary information or data that needs additional query time.\"), mdx(ImageComponent, {\n    fixed: \"default\",\n    caption: \"Expandable data table with one row expanded\",\n    mdxType: \"ImageComponent\"\n  }, mdx(\"span\", {\n    \"className\": \"gatsby-resp-image-wrapper\",\n    \"style\": {\n      \"position\": \"relative\",\n      \"display\": \"block\",\n      \"maxWidth\": \"1120px\",\n      \"marginLeft\": \"auto\",\n      \"marginRight\": \"auto\"\n    }\n  }, \"\\n    \", mdx(\"span\", _extends({\n    parentName: \"span\"\n  }, {\n    \"className\": \"gatsby-resp-image-background-image\",\n    \"style\": {\n      \"paddingBottom\": \"83.0163043478261%\",\n      \"position\": \"relative\",\n      \"bottom\": \"0px\",\n      \"left\": \"0px\",\n      \"backgroundSize\": \"cover\",\n      \"display\": \"block\"\n    }\n  })), \"\\n    \", mdx(\"img\", _extends({\n    parentName: \"span\"\n  }, {\n    \"className\": \"gatsby-resp-image-image\",\n    \"style\": {\n      \"width\": \"100%\",\n      \"height\": \"100%\",\n      \"margin\": \"0px\",\n      \"verticalAlign\": \"middle\",\n      \"position\": \"absolute\",\n      \"top\": \"0px\",\n      \"left\": \"0px\",\n      \"boxShadow\": \"inset 0px 0px 0px 400px transparent\"\n    },\n    \"alt\": \"Expandable data table with one row expanded.\",\n    \"title\": \"\",\n    \"src\": \"/static/eb1a84d71a5b0662a4ced332e8e6eb4e/24bd0/data-table-usage-11.png\",\n    \"srcSet\": [\"/static/eb1a84d71a5b0662a4ced332e8e6eb4e/7cb4c/data-table-usage-11.png 280w\", \"/static/eb1a84d71a5b0662a4ced332e8e6eb4e/7ff44/data-table-usage-11.png 560w\", \"/static/eb1a84d71a5b0662a4ced332e8e6eb4e/24bd0/data-table-usage-11.png 1120w\", \"/static/eb1a84d71a5b0662a4ced332e8e6eb4e/b4af2/data-table-usage-11.png 1472w\"],\n    \"sizes\": \"(max-width: 1120px) 100vw, 1120px\"\n  })), \"\\n  \")), mdx(\"p\", null, \"By default, the expand-all chevron is not shown. Keeping detailed information in expanded section saves user loading time by postponing some data queries until needed. Expanding all rows at once will typically negate this advantages of the expandable table. If additional load time is expected to display expanded information, use skeleton states instead of spinners.\"), mdx(ImageComponent, {\n    fixed: \"default\",\n    caption: \"Expandabling all rows with skeleton states\",\n    mdxType: \"ImageComponent\"\n  }, mdx(\"span\", {\n    \"className\": \"gatsby-resp-image-wrapper\",\n    \"style\": {\n      \"position\": \"relative\",\n      \"display\": \"block\",\n      \"maxWidth\": \"1120px\",\n      \"marginLeft\": \"auto\",\n      \"marginRight\": \"auto\"\n    }\n  }, \"\\n    \", mdx(\"span\", _extends({\n    parentName: \"span\"\n  }, {\n    \"className\": \"gatsby-resp-image-background-image\",\n    \"style\": {\n      \"paddingBottom\": \"82.33695652173913%\",\n      \"position\": \"relative\",\n      \"bottom\": \"0px\",\n      \"left\": \"0px\",\n      \"backgroundSize\": \"cover\",\n      \"display\": \"block\"\n    }\n  })), \"\\n    \", mdx(\"img\", _extends({\n    parentName: \"span\"\n  }, {\n    \"className\": \"gatsby-resp-image-image\",\n    \"style\": {\n      \"width\": \"100%\",\n      \"height\": \"100%\",\n      \"margin\": \"0px\",\n      \"verticalAlign\": \"middle\",\n      \"position\": \"absolute\",\n      \"top\": \"0px\",\n      \"left\": \"0px\",\n      \"boxShadow\": \"inset 0px 0px 0px 400px transparent\"\n    },\n    \"alt\": \"Expandabling all rows with skeleton states\",\n    \"title\": \"\",\n    \"src\": \"/static/14080956703cd9658e2aee5e140e3040/24bd0/data-table-usage-12.png\",\n    \"srcSet\": [\"/static/14080956703cd9658e2aee5e140e3040/7cb4c/data-table-usage-12.png 280w\", \"/static/14080956703cd9658e2aee5e140e3040/7ff44/data-table-usage-12.png 560w\", \"/static/14080956703cd9658e2aee5e140e3040/24bd0/data-table-usage-12.png 1120w\", \"/static/14080956703cd9658e2aee5e140e3040/b4af2/data-table-usage-12.png 1472w\"],\n    \"sizes\": \"(max-width: 1120px) 100vw, 1120px\"\n  })), \"\\n  \")));\n}\nMDXContent.isMDXComponent = true;"},"fields":{"slug":"/components/data-table/usage","currentPage":"usage"},"frontmatter":{"title":"Data table","label":null,"tabs":["Code","Usage","Style"],"internal":null}}},"pageContext":{"slug":"/components/data-table/usage","currentPage":"usage"}}